{"cameraMode":{"drawMode":0,"name":"Shaded","section":"Shading Mode"},"sceneLighting":true,"audioPlay":false,"sceneViewState":{"showFog":true,"showMaterialUpdate":false,"showSkybox":true,"showFlares":true,"showImageEffects":true,"showParticleSystems":true},"in2DMode":false,"pivot":{"x":4.477972030639648,"y":-1.5968856811523438,"z":55.1390495300293},"rotation":{"x":-0.15117020905017854,"y":-0.027576036751270295,"z":0.0042189802043139938,"w":-0.988114058971405},"size":126.88795471191406,"orthographic":false}